LICENSE
LICENSE.txt
README.md
pyproject.toml
upwork_cli/__init__.py
upwork_cli/__main__.py
upwork_cli/upcli.py
upwork_cli/utils.py
upwork_cli-0.1.0.dist-info/METADATA
upwork_cli-0.1.0.dist-info/WHEEL
upwork_cli-0.1.0.dist-info/entry_points.txt
upwork_cli-0.1.0.dist-info/licenses/LICENSE
upwork_cli-0.1.0.dist-info/licenses/LICENSE.txt
upwork_cli-0.1.0.dist-info/RECORD
