Metadata-Version: 2.4
Name: upwork-cli
Version: 0.1.0
Summary: Automate and streamline your Upwork freelancer workflow using the Upwork API.
Project-URL: Homepage, https://github.com/rsmahmud/upwork-cli
Project-URL: Issues, https://github.com/rsmahmud/upwork-cli/issues
Author-email: Hasan Rasel <rrss.mahmud@gmail.com>
License-Expression: MIT
License-File: LICENSE
License-File: LICENSE.txt
Keywords: api,developer,freelancer,python,upwork,upwork-api,upwork-python
Classifier: Operating System :: OS Independent
Classifier: Programming Language :: Python :: 3.10
Classifier: Programming Language :: Python :: 3.11
Classifier: Programming Language :: Python :: 3.12
Classifier: Programming Language :: Python :: 3.13
Classifier: Topic :: Internet :: WWW/HTTP :: Browsers
Classifier: Topic :: Software Development :: Libraries :: Python Modules
Requires-Python: >=3.9
Requires-Dist: colorlog
Requires-Dist: python-upwork
Requires-Dist: toasted
Provides-Extra: dev
Requires-Dist: hatchling; extra == 'dev'
Requires-Dist: uv-dynamic-versioning; extra == 'dev'
